[
  {
    "name": "迷客夏國際股份有限公司",
    "lat": null,
    "lng": null,
    "area": "苓雅區",
    "categories": [
      "飲品"
    ],
    "rating": null,
    "reviews": null
  },
  {
    "name": "茶湯會股份有限公司",
    "lat": null,
    "lng": null,
    "area": "小港區",
    "categories": [
      "飲品"
    ],
    "rating": null,
    "reviews": null
  },
  {
    "name": "清心福全-光華店",
    "lat": null,
    "lng": null,
    "area": "苓雅區",
    "categories": [
      "飲品"
    ],
    "rating": null,
    "reviews": null
  },
  {
    "name": "John捲可不可以",
    "lat": null,
    "lng": null,
    "area": "鳳山區",
    "categories": [
      "飲品"
    ],
    "rating": null,
    "reviews": null
  },
  {
    "name": "鮮茶道股份有限公司",
    "lat": null,
    "lng": null,
    "area": "三民區",
    "categories": [
      "飲品"
    ],
    "rating": null,
    "reviews": null
  },
  {
    "name": "精采好茶有限公司",
    "lat": null,
    "lng": null,
    "area": "新興區",
    "categories": [
      "飲品"
    ],
    "rating": null,
    "reviews": null
  },
  {
    "name": "清心福全股份有限公司",
    "lat": null,
    "lng": null,
    "area": "湖內區",
    "categories": [
      "飲品"
    ],
    "rating": null,
    "reviews": null
  },
  {
    "name": "幸福堂美食坊",
    "lat": null,
    "lng": null,
    "area": "三民區",
    "categories": [
      "飲品"
    ],
    "rating": null,
    "reviews": null
  },
  {
    "name": "來琳好茶",
    "lat": null,
    "lng": null,
    "area": "楠梓區",
    "categories": [
      "飲品"
    ],
    "rating": null,
    "reviews": null
  },
  {
    "name": "麻古有限公司",
    "lat": null,
    "lng": null,
    "area": "左營區",
    "categories": [
      "飲品"
    ],
    "rating": null,
    "reviews": null
  },
  {
    "name": "宋點好茶企業社",
    "lat": null,
    "lng": null,
    "area": "左營區",
    "categories": [
      "飲品"
    ],
    "rating": null,
    "reviews": null
  },
  {
    "name": "麻古茶坊股份有限公司",
    "lat": null,
    "lng": null,
    "area": "左營區",
    "categories": [
      "飲品"
    ],
    "rating": null,
    "reviews": null
  },
  {
    "name": "茶的魔手塩埕堀江店",
    "lat": null,
    "lng": null,
    "area": "鹽埕區",
    "categories": [
      "飲品"
    ],
    "rating": null,
    "reviews": null
  },
  {
    "name": "八曜和茶國際有限公司",
    "lat": null,
    "lng": null,
    "area": "三民區",
    "categories": [
      "飲品"
    ],
    "rating": null,
    "reviews": null
  },
  {
    "name": "八曜和茶專賣店",
    "lat": null,
    "lng": null,
    "area": "三民區",
    "categories": [
      "飲品"
    ],
    "rating": null,
    "reviews": null
  }
]